latexmake.py
setup.py
latexmake.egg-info/PKG-INFO
latexmake.egg-info/SOURCES.txt
latexmake.egg-info/dependency_links.txt
latexmake.egg-info/entry_points.txt
latexmake.egg-info/top_level.txt