Metadata-Version: 1.1
Name: latexmake
Version: 0.5dev
Summary: Latexmake completely automates the process of generating a LaTeX document.
Home-page: http://bitbucket.org/JanKanis/latexmake/
Author: Jan Kanis
Author-email: jan.code@jankanis.nl
License: GPLv3+
Platform: any
Classifier: Development Status :: 4 - Beta
Classifier: Intended Audience :: End Users/Desktop
Classifier: License :: OSI Approved :: GNU General Public License v3 or later (GPLv3+)
Classifier: Operating System :: OS Independent
Classifier: Programming Language :: Python
Classifier: Programming Language :: Python :: 3
Classifier: Topic :: Printing
Classifier: Topic :: Text Processing :: Markup :: LaTeX
